{
  "name": "Valhalla",
  "rooms": [
    {
      "id": 1233,
      "name": "The Chat Room",
      "exits": {
        "South": 1246
      }
    },
    {
      "id": 1234,
      "name": "Moses\u0027 Hangout",
      "exits": {
        "North": 1246
      }
    },
    {
      "id": 1235,
      "name": "The Center of the Universe",
      "exits": {
        "East": 1246
      }
    },
    {
      "id": 1255,
      "otherAreaExit": true,
      "name": "To Limbo",
      "exits": {}
    },
    {
      "id": 1236,
      "name": "Valhalla",
      "exits": {
        "North": 1242,
        "East": 1250,
        "South": 1241,
        "West": 1249,
        "Up": 1255
      }
    },
    {
      "id": 1237,
      "name": "Priscilla\u0027s Pleasure Palace ",
      "exits": {
        "North": 1251
      }
    },
    {
      "id": 1238,
      "name": "The Eye of the Hurricane",
      "exits": {}
    },
    {
      "id": 1239,
      "name": "Walking on the Moon",
      "exits": {}
    },
    {
      "id": 1240,
      "name": "The Satin Memorial Reading Room",
      "exits": {
        "South": 1250
      }
    },
    {
      "id": 1241,
      "name": "A Sea Cave",
      "exits": {
        "North": 1236
      }
    },
    {
      "id": 1242,
      "name": "The Archmage\u0027s Workroom",
      "exits": {
        "South": 1236
      }
    },
    {
      "id": 1243,
      "name": "Office",
      "exits": {
        "North": 1250
      }
    },
    {
      "id": 1244,
      "name": "Arena of Judgement",
      "exits": {
        "South": 1251
      }
    },
    {
      "id": 1245,
      "name": "The Realm of the Dead",
      "exits": {
        "North": 1245,
        "East": 1245,
        "South": 1245,
        "West": 1245
      }
    },
    {
      "id": 1246,
      "name": "Asgard",
      "exits": {
        "North": 1233,
        "East": 1249,
        "South": 1234,
        "West": 1235,
        "Down": 1248
      }
    },
    {
      "id": 1247,
      "name": "The Room of Lost Souls",
      "exits": {
        "Down": 1252
      }
    },
    {
      "id": 1504,
      "otherAreaExit": true,
      "name": "To Midgaard",
      "exits": {
        "Up": 1248
      }
    },
    {
      "id": 1248,
      "name": "Head of the Rainbow Bridge",
      "exits": {
        "Up": 1253,
        "Down": 1504
      }
    },
    {
      "id": 1249,
      "name": "The Entrance of Valhalla",
      "exits": {
        "East": 1236,
        "West": 1246
      }
    },
    {
      "id": 1250,
      "name": "Valhalla",
      "exits": {
        "North": 1240,
        "East": 1251,
        "South": 1243,
        "West": 1236,
        "Up": 1245
      }
    },
    {
      "id": 1256,
      "otherAreaExit": true,
      "name": "To Limbo",
      "exits": {}
    },
    {
      "id": 1251,
      "name": "Valhalla",
      "exits": {
        "North": 1244,
        "East": 1252,
        "South": 1237,
        "West": 1250,
        "Up": 1256
      }
    },
    {
      "id": 1554,
      "otherAreaExit": true,
      "name": "To Midgaard",
      "exits": {}
    },
    {
      "id": 1552,
      "otherAreaExit": true,
      "name": "To Midgaard",
      "exits": {}
    },
    {
      "id": 1555,
      "otherAreaExit": true,
      "name": "To Midgaard",
      "exits": {}
    },
    {
      "id": 1252,
      "name": "Valhalla",
      "exits": {
        "North": 1554,
        "East": 1552,
        "South": 1555,
        "West": 1251,
        "Up": 1247
      }
    },
    {
      "id": 1253,
      "name": "On the Rainbow Bridge",
      "exits": {
        "Up": 1254,
        "Down": 1248
      }
    },
    {
      "id": 1254,
      "name": "The End of the Rainbow Bridge",
      "exits": {
        "Up": 1246,
        "Down": 1253
      }
    }
  ]
}