{
  "Area": {
    "Name": "God Rooms",
    "Rooms": [
      {
        "Id": 1330,
        "Name": "The Chat Room",
        "IsExitToOtherArea": false,
        "Position": null,
        "Connections": {}
      },
      {
        "Id": 1331,
        "Name": "The HotTub",
        "IsExitToOtherArea": false,
        "Position": null,
        "Connections": {}
      },
      {
        "Id": 1332,
        "Name": "A Small Clearing",
        "IsExitToOtherArea": false,
        "Position": null,
        "Connections": {}
      },
      {
        "Id": 1333,
        "Name": "Ben\u0027s Room",
        "IsExitToOtherArea": false,
        "Position": null,
        "Connections": {}
      },
      {
        "Id": 1334,
        "Name": "Mephisto\u0027s Pad",
        "IsExitToOtherArea": false,
        "Position": null,
        "Connections": {
          "Up": 1335
        }
      },
      {
        "Id": 1335,
        "Name": "The Bathroom",
        "IsExitToOtherArea": false,
        "Position": null,
        "Connections": {
          "Down": 1334
        }
      },
      {
        "Id": 1336,
        "Name": "The Porch",
        "IsExitToOtherArea": false,
        "Position": null,
        "Connections": {
          "South": 1337,
          "Up": 1339
        }
      },
      {
        "Id": 1337,
        "Name": "The Living Room",
        "IsExitToOtherArea": false,
        "Position": null,
        "Connections": {
          "North": 1336,
          "West": 1338
        }
      },
      {
        "Id": 1338,
        "Name": "The Kitchen",
        "IsExitToOtherArea": false,
        "Position": null,
        "Connections": {
          "East": 1337
        }
      },
      {
        "Id": 1339,
        "Name": "Picard\u0027s Hideaway",
        "IsExitToOtherArea": false,
        "Position": null,
        "Connections": {
          "Down": 1336
        }
      },
      {
        "Id": 1340,
        "Name": "Katrina\u0027s Playpen",
        "IsExitToOtherArea": false,
        "Position": null,
        "Connections": {
          "West": 1341
        }
      },
      {
        "Id": 1341,
        "Name": "An Alcove",
        "IsExitToOtherArea": false,
        "Position": null,
        "Connections": {
          "East": 1340,
          "Up": 2247
        }
      },
      {
        "Id": 1342,
        "Name": "The Abyss",
        "IsExitToOtherArea": false,
        "Position": null,
        "Connections": {}
      },
      {
        "Id": 1343,
        "Name": "The Burning Shrine",
        "IsExitToOtherArea": false,
        "Position": null,
        "Connections": {}
      },
      {
        "Id": 1344,
        "Name": "Smoof\u0027s bedroom",
        "IsExitToOtherArea": false,
        "Position": null,
        "Connections": {
          "East": 1346,
          "North": 1345
        }
      },
      {
        "Id": 1345,
        "Name": "Smoof\u0027s bathroom",
        "IsExitToOtherArea": false,
        "Position": null,
        "Connections": {
          "South": 1344
        }
      },
      {
        "Id": 1346,
        "Name": "James\u0027 bedroom",
        "IsExitToOtherArea": false,
        "Position": null,
        "Connections": {
          "West": 1344
        }
      },
      {
        "Id": 1347,
        "Name": "Horizon",
        "IsExitToOtherArea": false,
        "Position": null,
        "Connections": {
          "Down": 1348
        }
      },
      {
        "Id": 1348,
        "Name": "The Hideout",
        "IsExitToOtherArea": false,
        "Position": null,
        "Connections": {
          "Up": 1347
        }
      },
      {
        "Id": 1349,
        "Name": "Alexander\u0027s private enclave",
        "IsExitToOtherArea": false,
        "Position": null,
        "Connections": {
          "South": 1350,
          "West": 1351
        }
      },
      {
        "Id": 1350,
        "Name": "Alexander\u0027s sleeping chamber",
        "IsExitToOtherArea": false,
        "Position": null,
        "Connections": {
          "North": 1349
        }
      },
      {
        "Id": 1351,
        "Name": "Alexander\u0027s laboratory",
        "IsExitToOtherArea": false,
        "Position": null,
        "Connections": {
          "East": 1349
        }
      },
      {
        "Id": 1352,
        "Name": "Wyrmclaw\u0027s Council of War Room",
        "IsExitToOtherArea": false,
        "Position": null,
        "Connections": {
          "South": 1330
        }
      },
      {
        "Id": 1353,
        "Name": "Zelda\u0027s Zany Zoo",
        "IsExitToOtherArea": false,
        "Position": null,
        "Connections": {}
      },
      {
        "Id": 2247,
        "Name": "To Midgaard",
        "IsExitToOtherArea": true,
        "Position": null,
        "Connections": {
          "North": 2296,
          "South": 2251,
          "Up": 3222
        }
      }
    ]
  },
  "BuildOptions": {
    "MaxSteps": 1000,
    "KeepSolitaryRooms": true,
    "KeepRoomsWithSingleOutsideExit": true,
    "FixObstacles": true,
    "FixNonStraight": true,
    "FixIntersected": true,
    "CompactMap": true,
    "AddDebugInfo": false,
    "ColorizeConnectionIssues": true
  }
}