{
  "Area": {
    "Name": "Little Haven",
    "Rooms": [
      {
        "Id": 1478,
        "Name": "The Big, Blue Ocean",
        "IsExitToOtherArea": false,
        "Position": null,
        "Connections": {
          "North": 2847,
          "West": 1479
        }
      },
      {
        "Id": 1479,
        "Name": "The Big, Blue Ocean",
        "IsExitToOtherArea": false,
        "Position": null,
        "Connections": {
          "South": 1480
        }
      },
      {
        "Id": 1480,
        "Name": "The Big, Blue Ocean",
        "IsExitToOtherArea": false,
        "Position": null,
        "Connections": {
          "South": 1481
        }
      },
      {
        "Id": 1481,
        "Name": "The Icy Waters",
        "IsExitToOtherArea": false,
        "Position": null,
        "Connections": {
          "South": 1482
        }
      },
      {
        "Id": 1482,
        "Name": "The Hardpack",
        "IsExitToOtherArea": false,
        "Position": null,
        "Connections": {
          "North": 1481,
          "South": 1483
        }
      },
      {
        "Id": 1483,
        "Name": "The Snow-filled Land",
        "IsExitToOtherArea": false,
        "Position": null,
        "Connections": {
          "North": 1482,
          "East": 1508,
          "South": 1509,
          "West": 1508
        }
      },
      {
        "Id": 1484,
        "Name": "The Gnome Outpost",
        "IsExitToOtherArea": false,
        "Position": null,
        "Connections": {
          "North": 1510,
          "Down": 1485
        }
      },
      {
        "Id": 1485,
        "Name": "The Tight Passage",
        "IsExitToOtherArea": false,
        "Position": null,
        "Connections": {
          "Up": 1484,
          "Down": 1486
        }
      },
      {
        "Id": 1486,
        "Name": "The Even Tighter Passage",
        "IsExitToOtherArea": false,
        "Position": null,
        "Connections": {
          "Up": 1485,
          "Down": 1487
        }
      },
      {
        "Id": 1487,
        "Name": "The Center Chamber",
        "IsExitToOtherArea": false,
        "Position": null,
        "Connections": {
          "East": 1488,
          "West": 1490
        }
      },
      {
        "Id": 1488,
        "Name": "A Passageway",
        "IsExitToOtherArea": false,
        "Position": null,
        "Connections": {
          "East": 1489,
          "West": 1487
        }
      },
      {
        "Id": 1489,
        "Name": "The Cold Passageway",
        "IsExitToOtherArea": false,
        "Position": null,
        "Connections": {
          "North": 1498,
          "West": 1488
        }
      },
      {
        "Id": 1490,
        "Name": "The Warm Passageway",
        "IsExitToOtherArea": false,
        "Position": null,
        "Connections": {
          "East": 1487,
          "West": 1493
        }
      },
      {
        "Id": 1491,
        "Name": "The Little Temple",
        "IsExitToOtherArea": false,
        "Position": null,
        "Connections": {
          "North": 1494,
          "South": 1492
        }
      },
      {
        "Id": 1492,
        "Name": "The Vestibule",
        "IsExitToOtherArea": false,
        "Position": null,
        "Connections": {
          "North": 1491,
          "South": 1495
        }
      },
      {
        "Id": 1493,
        "Name": "The Chanting Room",
        "IsExitToOtherArea": false,
        "Position": null,
        "Connections": {
          "North": 1495,
          "East": 1490
        }
      },
      {
        "Id": 1494,
        "Name": "The Furnace",
        "IsExitToOtherArea": false,
        "Position": null,
        "Connections": {
          "North": 1504,
          "South": 1491
        }
      },
      {
        "Id": 1495,
        "Name": "The Arboretum",
        "IsExitToOtherArea": false,
        "Position": null,
        "Connections": {
          "North": 1492,
          "East": 1497,
          "South": 1493
        }
      },
      {
        "Id": 1496,
        "Name": "The Snow Queen\u0027s Chamber",
        "IsExitToOtherArea": false,
        "Position": null,
        "Connections": {}
      },
      {
        "Id": 1497,
        "Name": "The Master Herbal\u0027s Room",
        "IsExitToOtherArea": false,
        "Position": null,
        "Connections": {
          "West": 1495,
          "Down": 1492
        }
      },
      {
        "Id": 1498,
        "Name": "The Guard\u0027s Dining Hall",
        "IsExitToOtherArea": false,
        "Position": null,
        "Connections": {
          "North": 1500,
          "East": 1499,
          "South": 1489
        }
      },
      {
        "Id": 1499,
        "Name": "The Vat Room",
        "IsExitToOtherArea": false,
        "Position": null,
        "Connections": {
          "West": 1498
        }
      },
      {
        "Id": 1500,
        "Name": "The Frost Giant Guard Quarters",
        "IsExitToOtherArea": false,
        "Position": null,
        "Connections": {
          "North": 1503,
          "South": 1498
        }
      },
      {
        "Id": 1501,
        "Name": "The White Dragon\u0027s Lair",
        "IsExitToOtherArea": false,
        "Position": null,
        "Connections": {
          "South": 1503,
          "North": 1502
        }
      },
      {
        "Id": 1502,
        "Name": "The Blue Dragon\u0027s Lair",
        "IsExitToOtherArea": false,
        "Position": null,
        "Connections": {
          "Down": 1499
        }
      },
      {
        "Id": 1503,
        "Name": "The connecting tunnel",
        "IsExitToOtherArea": false,
        "Position": null,
        "Connections": {
          "North": 1501,
          "South": 1500
        }
      },
      {
        "Id": 1504,
        "Name": "The Great Door",
        "IsExitToOtherArea": false,
        "Position": null,
        "Connections": {
          "North": 1505,
          "South": 1494
        }
      },
      {
        "Id": 1505,
        "Name": "The Snow Queen\u0027s Entry Hall",
        "IsExitToOtherArea": false,
        "Position": null,
        "Connections": {
          "North": 1506,
          "East": 1506,
          "South": 1504,
          "West": 1506
        }
      },
      {
        "Id": 1506,
        "Name": "Another Mirrored Room",
        "IsExitToOtherArea": false,
        "Position": null,
        "Connections": {
          "North": 1507,
          "East": 1505,
          "South": 1505,
          "West": 1505
        }
      },
      {
        "Id": 1507,
        "Name": "Another Mirrored Room",
        "IsExitToOtherArea": false,
        "Position": null,
        "Connections": {
          "North": 1496,
          "East": 1507,
          "South": 1506,
          "West": 1507
        }
      },
      {
        "Id": 1508,
        "Name": "The Snow-filled Land",
        "IsExitToOtherArea": false,
        "Position": null,
        "Connections": {
          "North": 1509,
          "East": 1483,
          "South": 1510,
          "West": 1483
        }
      },
      {
        "Id": 1509,
        "Name": "The Snow-filled Land",
        "IsExitToOtherArea": false,
        "Position": null,
        "Connections": {
          "North": 1483,
          "East": 1510,
          "South": 1508,
          "West": 1510
        }
      },
      {
        "Id": 1510,
        "Name": "The Snow-filled Land",
        "IsExitToOtherArea": false,
        "Position": null,
        "Connections": {
          "North": 1508,
          "East": 1509,
          "South": 1484,
          "West": 1509
        }
      },
      {
        "Id": 2847,
        "Name": "To The River",
        "IsExitToOtherArea": true,
        "Position": null,
        "Connections": {
          "North": 2840,
          "West": 2848,
          "South": 1478
        }
      }
    ]
  },
  "BuildOptions": {
    "MaxSteps": 1000,
    "KeepSolitaryRooms": true,
    "KeepRoomsWithSingleOutsideExit": true,
    "FixObstacles": true,
    "FixNonStraight": true,
    "FixIntersected": true,
    "CompactMap": true,
    "AddDebugInfo": false,
    "ColorizeConnectionIssues": true
  }
}